MANIFEST.in
README.rst
setup.py
spark_test/__init__.py
spark_test/helpers.py
spark_test/testing.py
spark_test.egg-info/PKG-INFO
spark_test.egg-info/SOURCES.txt
spark_test.egg-info/dependency_links.txt
spark_test.egg-info/requires.txt
spark_test.egg-info/top_level.txt