Metadata-Version: 1.1
Name: spark-test
Version: 0.2.8
Summary: Assertion functions to test Spark Collections like DataFrames.
Home-page: https://github.com/tomasfarias/spark-test
Author: Tomas Farias
Author-email: tomasfariassantana@gmail.com
License: MIT
Platform: UNKNOWN
Classifier: Development Status :: 3 - Alpha
Classifier: License :: OSI Approved :: MIT License
Classifier: Intended Audience :: Developers
Classifier: Topic :: Software Development :: Testing
Classifier: Programming Language :: Python
Classifier: Programming Language :: Python :: 3.7
Classifier: Programming Language :: Python :: 3.6
Classifier: Operating System :: OS Independent
